Metadata-Version: 2.1
Name: krauss-misc
Version: 0.9.6
Summary: package of misc code that supports other projects of mine
Home-page: https://github.com/ryanGT/krauss_misc
Author: Ryan Krauss
Author-email: ryanwkrauss@gmail.com
Classifier: Programming Language :: Python :: 3
Classifier: License :: OSI Approved :: MIT License
Classifier: Operating System :: OS Independent
